{
  "active": false,
  "connections": {
    "Start": {
      "main": [
        [
          {
            "node": "HTTP Request",
            "type": "main",
            "index": 0
          }
        ]
      ]
    }
  },
  "createdAt": "2023-08-11T07:17:48.370Z",
  "id": "347",
  "name": "Automation for old shipment creation",
  "nodes": [
    {
      "parameters": {},
      "name": "Start",
      "type": "n8n-nodes-base.start",
      "typeVersion": 1,
      "position": [
        240,
        300
      ]
    },
    {
      "parameters": {
        "requestMethod": "POST",
        "jsonParameters": true,
        "options": {
          "bodyContentType": "multipart-form-data"
        },
        "sendBinaryData": true
      },
      "name": "HTTP Request",
      "type": "n8n-nodes-base.httpRequest",
      "typeVersion": 1,
      "position": [
        460,
        300
      ]
    }
  ],
  "settings": {},
  "staticData": null,
  "tags": [],
  "updatedAt": "2023-08-11T07:17:48.370Z"
}